Verilog Code/fifo.v
module fifo #(
    parameter DATA_WIDTH = 8,
    parameter ADDR_WIDTH = 4
)(
    input clk,
    input reset,
    input rd,           // Read enable
    input wr,           // Write enable
    input [DATA_WIDTH-1:0] w_data,  // Data to write
    output full,
    output empty,
    output [DATA_WIDTH-1:0] r_data  // Data read
);

    // Local parameters
    localparam DEPTH = 1 << ADDR_WIDTH;

    // Internal signals
    reg [DATA_WIDTH-1:0] fifo_mem [0:DEPTH-1];
    reg [ADDR_WIDTH-1:0] w_ptr_reg, w_ptr_next;
    reg [ADDR_WIDTH-1:0] r_ptr_reg, r_ptr_next;
    reg [ADDR_WIDTH:0]   count_reg, count_next;  // one extra bit for full detection
    reg [DATA_WIDTH-1:0] r_data_reg;

    // Write and read pointers
    always @(posedge clk or posedge reset) begin
        if (reset) begin
            w_ptr_reg <= 0;
            r_ptr_reg <= 0;
            count_reg <= 0;
            r_data_reg <= 0;
        end else begin
            w_ptr_reg <= w_ptr_next;
            r_ptr_reg <= r_ptr_next;
            count_reg <= count_next;

            if (rd && ~empty)
                r_data_reg <= fifo_mem[r_ptr_reg];
        end
    end

    // Write logic
    always @(posedge clk) begin
        if (wr && ~full)
            fifo_mem[w_ptr_reg] <= w_data;
    end

    // Next pointer and count logic
    always @(*) begin
        w_ptr_next = w_ptr_reg;
        r_ptr_next = r_ptr_reg;
        count_next = count_reg;

        if (wr && ~full)
            w_ptr_next = w_ptr_reg + 1;

        if (rd && ~empty)
            r_ptr_next = r_ptr_reg + 1;

        case ({wr && ~full, rd && ~empty})
            2'b10: count_next = count_reg + 1; // write only
            2'b01: count_next = count_reg - 1; // read only
            default: count_next = count_reg;   // no change or simultaneous read/write
        endcase
    end

    // Output signals
    assign full  = (count_reg == DEPTH);
    assign empty = (count_reg == 0);
    assign r_data = r_data_reg;

endmodule

Verilog_Codes/tx.v
module uart_tx #(
    parameter DBIT = 8,
    parameter SB_TICK = 16
)(
    input clk,
    input reset,
    input tx_start,
    input s_tick,
    input [7:0] din,
    output reg tx_done_tick,
    output tx
);

    // FSM state encoding
    localparam [1:0] IDLE  = 2'b00,
                     START = 2'b01,
                     DATA  = 2'b10,
                     STOP  = 2'b11;

    // Internal signals
    reg [1:0] state_reg, state_next;
    reg [3:0] s_reg, s_next;
    reg [2:0] n_reg, n_next;
    reg [7:0] b_reg, b_next;
    reg tx_reg, tx_next;

    // State and data registers
    always @(posedge clk or posedge reset) begin
        if (reset) begin
            state_reg <= IDLE;
            s_reg <= 4'd0;
            n_reg <= 3'd0;
            b_reg <= 8'd0;
            tx_reg <= 1'b1;
        end else begin
            state_reg <= state_next;
            s_reg <= s_next;
            n_reg <= n_next;
            b_reg <= b_next;
            tx_reg <= tx_next;
        end
    end

    // Next-state logic
    always @(*) begin
        // Default assignments
        state_next = state_reg;
        tx_done_tick = 1'b0;
        s_next = s_reg;
        n_next = n_reg;
        b_next = b_reg;
        tx_next = tx_reg;

        case (state_reg)
            IDLE: begin
                tx_next = 1'b1;
                if (tx_start) begin
                    state_next = START;
                    s_next = 4'd0;
                    b_next = din;
                end
            end

            START: begin
                tx_next = 1'b0;
                if (s_tick) begin
                    if (s_reg == 4'd15) begin
                        state_next = DATA;
                        s_next = 4'd0;
                        n_next = 3'd0;
                    end else begin
                        s_next = s_reg + 1;
                    end
                end
            end

            DATA: begin
                tx_next = b_reg[0];
                if (s_tick) begin
                    if (s_reg == 4'd15) begin
                        s_next = 4'd0;
                        b_next = b_reg >> 1;
                        if (n_reg == (DBIT - 1)) begin
                            state_next = STOP;
                        end else begin
                            n_next = n_reg + 1;
                        end
                    end else begin
                        s_next = s_reg + 1;
                    end
                end
            end

            STOP: begin
                tx_next = 1'b1;
                if (s_tick) begin
                    if (s_reg == (SB_TICK - 1)) begin
                        state_next = IDLE;
                        tx_done_tick = 1'b1;
                    end else begin
                        s_next = s_reg + 1;
                    end
                end
            end
        endcase
    end

    // Output assignment
    assign tx = tx_reg;

endmodule

Verilog Code/rx.v
module uart_rx #(
    parameter DBIT = 8,
    parameter SB_TICK = 16
)(
    input clk,
    input reset,
    input rx,
    input s_tick,
    output reg rx_done_tick,
    output [7:0] dout
);

    // State declarations
    localparam [1:0] IDLE  = 2'b00,
                     START = 2'b01,
                     DATA  = 2'b10,
                     STOP  = 2'b11;

    // Signal declarations
    reg [1:0] state_reg, state_next;
    reg [3:0] s_reg, s_next;
    reg [2:0] n_reg, n_next;
    reg [7:0] b_reg, b_next;

    // FSMD state & data registers
    always @(posedge clk or posedge reset) begin
        if (reset) begin
            state_reg <= IDLE;
            s_reg <= 4'd0;
            n_reg <= 3'd0;
            b_reg <= 8'd0;
        end else begin
            state_reg <= state_next;
            s_reg <= s_next;
            n_reg <= n_next;
            b_reg <= b_next;
        end
    end

    // FSMD next-state logic
    always @(*) begin
        // Default assignments
        state_next = state_reg;
        rx_done_tick = 1'b0;
        s_next = s_reg;
        n_next = n_reg;
        b_next = b_reg;

        case (state_reg)
            IDLE: begin
                if (~rx) begin  // Start bit is LOW
                    state_next = START;
                    s_next = 4'd0;
                end
            end

            START: begin
                if (s_tick) begin
                    if (s_reg == 4'd7) begin
                        state_next = DATA;
                        s_next = 4'd0;
                        n_next = 3'd0;
                    end else begin
                        s_next = s_reg + 1;
                    end
                end
            end

            DATA: begin
                if (s_tick) begin
                    if (s_reg == 4'd15) begin
                        s_next = 4'd0;
                        b_next = {rx, b_reg[7:1]};  // shift right
                        if (n_reg == (DBIT - 1)) begin
                            state_next = STOP;
                        end else begin
                            n_next = n_reg + 1;
                        end
                    end else begin
                        s_next = s_reg + 1;
                    end
                end
            end

            STOP: begin
                if (s_tick) begin
                    if (s_reg == (SB_TICK - 1)) begin
                        state_next = IDLE;
                        rx_done_tick = 1'b1;
                    end else begin
                        s_next = s_reg + 1;
                    end
                end
            end
        endcase
    end

    // Output assignment
    assign dout = b_reg;

endmodule

Verilog_Codes/brg.v
module baud_gen (
    input clk,
    input reset,
    input [10:0] dvsr,
    output tick
);

    // Internal signal declarations
    reg [10:0] r_reg;
    wire [10:0] r_next;

    // Register (sequential logic)
    always @(posedge clk or posedge reset) begin
        if (reset)
            r_reg <= 11'd0;
        else
            r_reg <= r_next;
    end

    // Next-state logic
    assign r_next = (r_reg == dvsr) ? 11'd0 : r_reg + 11'd1;

    // Output logic
    assign tick = (r_reg == 11'd1);

endmodule

Verilog Code/uart.v
`include "brg.v"
`include "rx.v"
`include "tx.v"
`include "fifo.v"

module UART #(
    parameter DBIT = 8,
    parameter SB_TICK = 16,
    parameter FIFO_W = 2
)(
    input clk, reset, rd_uart, wr_uart, rx,
    input [7:0] w_data,
    input [10:0] dvsr,
    output tx_full, rx_empty, tx,
    output [7:0] r_data
);

    // Internal signal declarations
    wire tick, rx_done_tick, tx_done_tick;
    wire tx_empty, tx_fifo_not_empty;
    wire [7:0] tx_fifo_out, rx_data_out;

    // Instantiate baud generator
    baud_gen baud_gen_unit (
        .clk(clk),
        .reset(reset),
        .dvsr(dvsr),
        .tick(tick)
    );

    // Instantiate UART Receiver
    uart_rx #(.DBIT(DBIT), .SB_TICK(SB_TICK)) uart_rx_unit (
        .clk(clk),
        .reset(reset),
        .rx(rx),
        .s_tick(tick),
        .rx_done_tick(rx_done_tick),
        .dout(rx_data_out)
    );

    // Instantiate UART Transmitter
    uart_tx #(.DBIT(DBIT), .SB_TICK(SB_TICK)) uart_tx_unit (
        .clk(clk),
        .reset(reset),
        .tx_start(tx_fifo_not_empty),
        .s_tick(tick),
        .din(tx_fifo_out),
        .tx_done_tick(tx_done_tick),
        .tx(tx)
    );

    // Instantiate RX FIFO
    fifo #(.DATA_WIDTH(DBIT), .ADDR_WIDTH(FIFO_W)) fifo_rx_unit (
        .clk(clk),
        .reset(reset),
        .rd(rd_uart),
        .wr(rx_done_tick),
        .w_data(rx_data_out),
        .empty(rx_empty),
        .full(),  // Unused
        .r_data(r_data)
    );

    // Instantiate TX FIFO
    fifo #(.DATA_WIDTH(DBIT), .ADDR_WIDTH(FIFO_W)) fifo_tx_unit (
        .clk(clk),
        .reset(reset),
        .rd(tx_done_tick),
        .wr(wr_uart),
        .w_data(w_data),
        .empty(tx_empty),
        .full(tx_full),
        .r_data(tx_fifo_out)
    );

    // Internal combinational logic
    assign tx_fifo_not_empty = ~tx_empty;

endmodule

Verilog Code/tb_uart.v
`timescale 1ns/1ps

module tb_uart;

    // Parameters
    localparam DBIT = 8;
    localparam SB_TICK = 16;
    localparam FIFO_W = 2;

    // Signals
    reg clk;
    reg reset;
    reg rd_uart, wr_uart;
    reg [7:0] w_data;
    reg [10:0] dvsr;
    wire tx_full, rx_empty;
    wire tx;
    wire [7:0] r_data;
    wire rx;

    // UART Loopback: tx connected to rx
    assign rx = tx;

    // Instantiate UART module directly
    UART #(.DBIT(DBIT), .SB_TICK(SB_TICK), .FIFO_W(FIFO_W)) uut (
        .clk(clk),
        .reset(reset),
        .rd_uart(rd_uart),
        .wr_uart(wr_uart),
        .rx(rx),
        .w_data(w_data),
        .dvsr(dvsr),
        .tx_full(tx_full),
        .rx_empty(rx_empty),
        .tx(tx),
        .r_data(r_data)
    );

    // Clock generation: 50 MHz
    initial begin
        clk = 0;
        forever #10 clk = ~clk; // 20ns period
    end

    // Test sequence
    initial begin
        $dumpfile("uart.vcd");
        $dumpvars(0, tb_uart);

        // Init
        reset = 1;
        rd_uart = 0;
        wr_uart = 0;
        w_data = 8'd0;
        dvsr = 11'd4; // Fast simulation (very high baud rate)
        #100;

        reset = 0;
        #100;

        send_byte(8'h41); // A
        send_byte(8'h42); // B
        send_byte(8'h43); // C

        #5000;
        $display("Simulation finished.");
        $finish;
    end

    // Task to send a byte over UART
    task send_byte(input [7:0] byte);
        begin
            // Wait until TX not full
            wait (!tx_full);
            @(posedge clk);
            wr_uart = 1;
            w_data = byte;
            @(posedge clk);
            wr_uart = 0;
            w_data = 8'd0;

            // Wait until RX is not empty
            wait (!rx_empty);
            @(posedge clk);
            rd_uart = 1;
            @(posedge clk);
            rd_uart = 0;

            @(posedge clk);
            @(posedge clk);

            if (r_data >= 32 && r_data <= 126)
                $display("Time %0t: Received byte: 0x%0h ('%c')", $time, r_data, r_data);
            else
                $display("Time %0t: Received byte: 0x%0h ('?')", $time, r_data);

            #1000;
        end
    endtask

endmodule

Verilog_Codes/uart.vcd
$date
	Wed Jun 18 13:37:08 2025
$end
$version
	Icarus Verilog
$end
$timescale
	1ps
$end
$scope module tb_uart $end
$var wire 1 ! rx $end
$var wire 1 " tx_full $end
$var wire 1 # tx $end
$var wire 1 $ rx_empty $end
$var wire 8 % r_data [7:0] $end
$var parameter 32 & DBIT $end
$var parameter 32 ' FIFO_W $end
$var parameter 32 ( SB_TICK $end
$var reg 1 ) clk $end
$var reg 11 * dvsr [10:0] $end
$var reg 1 + rd_uart $end
$var reg 1 , reset $end
$var reg 8 - w_data [7:0] $end
$var reg 1 . wr_uart $end
$scope module uut $end
$var wire 1 ) clk $end
$var wire 11 / dvsr [10:0] $end
$var wire 1 + rd_uart $end
$var wire 1 , reset $end
$var wire 1 ! rx $end
$var wire 1 0 tx_fifo_not_empty $end
$var wire 8 1 w_data [7:0] $end
$var wire 1 . wr_uart $end
$var wire 1 " tx_full $end
$var wire 8 2 tx_fifo_out [7:0] $end
$var wire 1 3 tx_empty $end
$var wire 1 4 tx_done_tick $end
$var wire 1 # tx $end
$var wire 1 5 tick $end
$var wire 1 $ rx_empty $end
$var wire 1 6 rx_done_tick $end
$var wire 8 7 rx_data_out [7:0] $end
$var wire 8 8 r_data [7:0] $end
$var parameter 32 9 DBIT $end
$var parameter 32 : FIFO_W $end
$var parameter 32 ; SB_TICK $end
$scope module baud_gen_unit $end
$var wire 1 ) clk $end
$var wire 11 < dvsr [10:0] $end
$var wire 1 , reset $end
$var wire 1 5 tick $end
$var wire 11 = r_next [10:0] $end
$var reg 11 > r_reg [10:0] $end
$upscope $end
$scope module fifo_rx_unit $end
$var wire 1 ) clk $end
$var wire 8 ? r_data [7:0] $end
$var wire 1 + rd $end
$var wire 1 , reset $end
$var wire 1 6 wr $end
$var wire 8 @ w_data [7:0] $end
$var wire 1 A full $end
$var wire 1 $ empty $end
$var parameter 32 B ADDR_WIDTH $end
$var parameter 32 C DATA_WIDTH $end
$var parameter 34 D DEPTH $end
$var reg 3 E count_next [2:0] $end
$var reg 3 F count_reg [2:0] $end
$var reg 8 G r_data_reg [7:0] $end
$var reg 2 H r_ptr_next [1:0] $end
$var reg 2 I r_ptr_reg [1:0] $end
$var reg 2 J w_ptr_next [1:0] $end
$var reg 2 K w_ptr_reg [1:0] $end
$upscope $end
$scope module fifo_tx_unit $end
$var wire 1 ) clk $end
$var wire 8 L r_data [7:0] $end
$var wire 1 , reset $end
$var wire 8 M w_data [7:0] $end
$var wire 1 . wr $end
$var wire 1 4 rd $end
$var wire 1 " full $end
$var wire 1 3 empty $end
$var parameter 32 N ADDR_WIDTH $end
$var parameter 32 O DATA_WIDTH $end
$var parameter 34 P DEPTH $end
$var reg 3 Q count_next [2:0] $end
$var reg 3 R count_reg [2:0] $end
$var reg 8 S r_data_reg [7:0] $end
$var reg 2 T r_ptr_next [1:0] $end
$var reg 2 U r_ptr_reg [1:0] $end
$var reg 2 V w_ptr_next [1:0] $end
$var reg 2 W w_ptr_reg [1:0] $end
$upscope $end
$scope module uart_rx_unit $end
$var wire 1 ) clk $end
$var wire 8 X dout [7:0] $end
$var wire 1 , reset $end
$var wire 1 ! rx $end
$var wire 1 5 s_tick $end
$var parameter 2 Y DATA $end
$var parameter 32 Z DBIT $end
$var parameter 2 [ IDLE $end
$var parameter 32 \ SB_TICK $end
$var parameter 2 ] START $end
$var parameter 2 ^ STOP $end
$var reg 8 _ b_next [7:0] $end
$var reg 8 ` b_reg [7:0] $end
$var reg 3 a n_next [2:0] $end
$var reg 3 b n_reg [2:0] $end
$var reg 1 6 rx_done_tick $end
$var reg 4 c s_next [3:0] $end
$var reg 4 d s_reg [3:0] $end
$var reg 2 e state_next [1:0] $end
$var reg 2 f state_reg [1:0] $end
$upscope $end
$scope module uart_tx_unit $end
$var wire 1 ) clk $end
$var wire 8 g din [7:0] $end
$var wire 1 , reset $end
$var wire 1 5 s_tick $end
$var wire 1 0 tx_start $end
$var wire 1 # tx $end
$var parameter 2 h DATA $end
$var parameter 32 i DBIT $end
$var parameter 2 j IDLE $end
$var parameter 32 k SB_TICK $end
$var parameter 2 l START $end
$var parameter 2 m STOP $end
$var reg 8 n b_next [7:0] $end
$var reg 8 o b_reg [7:0] $end
$var reg 3 p n_next [2:0] $end
$var reg 3 q n_reg [2:0] $end
$var reg 4 r s_next [3:0] $end
$var reg 4 s s_reg [3:0] $end
$var reg 2 t state_next [1:0] $end
$var reg 2 u state_reg [1:0] $end
$var reg 1 4 tx_done_tick $end
$var reg 1 v tx_next $end
$var reg 1 # tx_reg $end
$upscope $end
$upscope $end
$scope task send_byte $end
$var reg 8 w byte [7:0] $end
$upscope $end
$upscope $end
$enddefinitions $end
$comment Show the parameter values. $end
$dumpall
b11 m
b1 l
b10000 k
b0 j
b1000 i
b10 h
b11 ^
b1 ]
b10000 \
b0 [
b1000 Z
b10 Y
b100 P
b1000 O
b10 N
b100 D
b1000 C
b10 B
b10000 ;
b10 :
b1000 9
b10000 (
b10 '
b1000 &
$end
#0
$dumpvars
bx w
1v
b0 u
b0 t
b0 s
b0 r
b0 q
b0 p
b0 o
b0 n
b0 g
b0 f
b0 e
b0 d
b0 c
b0 b
b0 a
b0 `
b0 _
b0 X
b0 W
b0 V
b0 U
b0 T
b0 S
b0 R
b0 Q
b0 M
b0 L
b0 K
b0 J
b0 I
b0 H
b0 G
b0 F
b0 E
0A
b0 @
b0 ?
b0 >
b1 =
b100 <
b0 8
b0 7
06
05
04
13
b0 2
b0 1
00
b100 /
0.
b0 -
1,
0+
b100 *
0)
b0 %
1$
1#
0"
1!
$end
#10000
1)
#20000
0)
#30000
1)
#40000
0)
#50000
1)
#60000
0)
#70000
1)
#80000
0)
#90000
1)
#100000
0)
0,
#110000
b10 =
15
b1 >
1)
#120000
0)
#130000
b11 =
05
b10 >
1)
#140000
0)
#150000
b100 =
b11 >
1)
#160000
0)
#170000
b0 =
b100 >
1)
#180000
0)
#190000
b1 =
b0 >
1)
#200000
0)
b1000001 w
#210000
b10 =
15
b1 >
b1 Q
b1 V
b1000001 -
b1000001 1
b1000001 M
1.
1)
#220000
0)
#230000
b11 =
b1 t
10
05
b10 >
03
b1 R
b1 W
b1 Q
b1 V
b0 -
b0 1
b0 M
0.
1)
#240000
0)
#250000
0v
b100 =
b1 u
b11 >
1)
#260000
0)
#270000
b0 =
b1 e
b100 >
0!
0#
1)
#280000
0)
#290000
b1 =
b1 f
b0 >
1)
#300000
0)
#310000
b10 =
b1 c
b1 r
15
b1 >
1)
#320000
0)
#330000
b11 =
b1 s
b1 d
05
b10 >
1)
#340000
0)
#350000
b100 =
b11 >
1)
#360000
0)
#370000
b0 =
b100 >
1)
#380000
0)
#390000
b1 =
b0 >
1)
#400000
0)
#410000
b10 =
b10 c
b10 r
15
b1 >
1)
#420000
0)
#430000
b11 =
05
b10 >
b10 d
b10 s
1)
#440000
0)
#450000
b100 =
b11 >
1)
#460000
0)
#470000
b0 =
b100 >
1)
#480000
0)
#490000
b1 =
b0 >
1)
#500000
0)
#510000
b10 =
b11 c
b11 r
15
b1 >
1)
#520000
0)
#530000
b11 =
b11 s
b11 d
05
b10 >
1)
#540000
0)
#550000
b100 =
b11 >
1)
#560000
0)
#570000
b0 =
b100 >
1)
#580000
0)
#590000
b1 =
b0 >
1)
#600000
0)
#610000
b10 =
b100 c
b100 r
15
b1 >
1)
#620000
0)
#630000
b11 =
05
b10 >
b100 d
b100 s
1)
#640000
0)
#650000
b100 =
b11 >
1)
#660000
0)
#670000
b0 =
b100 >
1)
#680000
0)
#690000
b1 =
b0 >
1)
#700000
0)
#710000
b10 =
b101 c
b101 r
15
b1 >
1)
#720000
0)
#730000
b11 =
b101 s
b101 d
05
b10 >
1)
#740000
0)
#750000
b100 =
b11 >
1)
#760000
0)
#770000
b0 =
b100 >
1)
#780000
0)
#790000
b1 =
b0 >
1)
#800000
0)
#810000
b10 =
b110 c
b110 r
15
b1 >
1)
#820000
0)
#830000
b11 =
05
b10 >
b110 d
b110 s
1)
#840000
0)
#850000
b100 =
b11 >
1)
#860000
0)
#870000
b0 =
b100 >
1)
#880000
0)
#890000
b1 =
b0 >
1)
#900000
0)
#910000
b10 =
b111 c
b111 r
15
b1 >
1)
#920000
0)
#930000
b11 =
b111 s
b111 d
05
b10 >
1)
#940000
0)
#950000
b100 =
b11 >
1)
#960000
0)
#970000
b0 =
b100 >
1)
#980000
0)
#990000
b1 =
b0 >
1)
#1000000
0)
#1010000
b10 =
b0 c
b10 e
b1000 r
15
b1 >
1)
#1020000
0)
#1030000
b11 =
05
b10 >
b0 d
b10 f
b1000 s
1)
#1040000
0)
#1050000
b100 =
b11 >
1)
#1060000
0)
#1070000
b0 =
b100 >
1)
#1080000
0)
#1090000
b1 =
b0 >
1)
#1100000
0)
#1110000
b10 =
b1 c
b1001 r
15
b1 >
1)
#1120000
0)
#1130000
b11 =
b1001 s
b1 d
05
b10 >
1)
#1140000
0)
#1150000
b100 =
b11 >
1)
#1160000
0)
#1170000
b0 =
b100 >
1)
#1180000
0)
#1190000
b1 =
b0 >
1)
#1200000
0)
#1210000
b10 =
b10 c
b1010 r
15
b1 >
1)
#1220000
0)
#1230000
b11 =
05
b10 >
b10 d
b1010 s
1)
#1240000
0)
#1250000
b100 =
b11 >
1)
#1260000
0)
#1270000
b0 =
b100 >
1)
#1280000
0)
#1290000
b1 =
b0 >
1)
#1300000
0)
#1310000
b10 =
b11 c
b1011 r
15
b1 >
1)
#1320000
0)
#1330000
b11 =
b1011 s
b11 d
05
b10 >
1)
#1340000
0)
#1350000
b100 =
b11 >
1)
#1360000
0)
#1370000
b0 =
b100 >
1)
#1380000
0)
#1390000
b1 =
b0 >
1)
#1400000
0)
#1410000
b10 =
b100 c
b1100 r
15
b1 >
1)
#1420000
0)
#1430000
b11 =
05
b10 >
b100 d
b1100 s
1)
#1440000
0)
#1450000
b100 =
b11 >
1)
#1460000
0)
#1470000
b0 =
b100 >
1)
#1480000
0)
#1490000
b1 =
b0 >
1)
#1500000
0)
#1510000
b10 =
b101 c
b1101 r
15
b1 >
1)
#1520000
0)
#1530000
b11 =
b1101 s
b101 d
05
b10 >
1)
#1540000
0)
#1550000
b100 =
b11 >
1)
#1560000
0)
#1570000
b0 =
b100 >
1)
#1580000
0)
#1590000
b1 =
b0 >
1)
#1600000
0)
#1610000
b10 =
b110 c
b1110 r
15
b1 >
1)
#1620000
0)
#1630000
b11 =
05
b10 >
b110 d
b1110 s
1)
#1640000
0)
#1650000
b100 =
b11 >
1)
#1660000
0)
#1670000
b0 =
b100 >
1)
#1680000
0)
#1690000
b1 =
b0 >
1)
#1700000
0)
#1710000
b10 =
b111 c
b1111 r
15
b1 >
1)
#1720000
0)
#1730000
b11 =
b1111 s
b111 d
05
b10 >
1)
#1740000
0)
#1750000
b100 =
b11 >
1)
#1760000
0)
#1770000
b0 =
b100 >
1)
#1780000
0)
#1790000
b1 =
b0 >
1)
#1800000
0)
#1810000
b10 =
b1000 c
b0 r
b10 t
15
b1 >
1)
#1820000
0)
#1830000
b11 =
05
b10 >
b1000 d
b0 s
b10 u
1)
#1840000
0)
#1850000
b100 =
b11 >
1)
#1860000
0)
#1870000
b0 =
b100 >
1)
#1880000
0)
#1890000
b1 =
b0 >
1)
#1900000
0)
#1910000
b10 =
b1001 c
b1 r
15
b1 >
1)
#1920000
0)
#1930000
b11 =
b1 s
b1001 d
05
b10 >
1)
#1940000
0)
#1950000
b100 =
b11 >
1)
#1960000
0)
#1970000
b0 =
b100 >
1)
#1980000
0)
#1990000
b1 =
b0 >
1)
#2000000
0)
#2010000
b10 =
b1010 c
b10 r
15
b1 >
1)
#2020000
0)
#2030000
b11 =
05
b10 >
b1010 d
b10 s
1)
#2040000
0)
#2050000
b100 =
b11 >
1)
#2060000
0)
#2070000
b0 =
b100 >
1)
#2080000
0)
#2090000
b1 =
b0 >
1)
#2100000
0)
#2110000
b10 =
b1011 c
b11 r
15
b1 >
1)
#2120000
0)
#2130000
b11 =
b11 s
b1011 d
05
b10 >
1)
#2140000
0)
#2150000
b100 =
b11 >
1)
#2160000
0)
#2170000
b0 =
b100 >
1)
#2180000
0)
#2190000
b1 =
b0 >
1)
#2200000
0)
#2210000
b10 =
b1100 c
b100 r
15
b1 >
1)
#2220000
0)
#2230000
b11 =
05
b10 >
b1100 d
b100 s
1)
#2240000
0)
#2250000
b100 =
b11 >
1)
#2260000
0)
#2270000
b0 =
b100 >
1)
#2280000
0)
#2290000
b1 =
b0 >
1)
#2300000
0)
#2310000
b10 =
b1101 c
b101 r
15
b1 >
1)
#2320000
0)
#2330000
b11 =
b101 s
b1101 d
05
b10 >
1)
#2340000
0)
#2350000
b100 =
b11 >
1)
#2360000
0)
#2370000
b0 =
b100 >
1)
#2380000
0)
#2390000
b1 =
b0 >
1)
#2400000
0)
#2410000
b10 =
b1110 c
b110 r
15
b1 >
1)
#2420000
0)
#2430000
b11 =
05
b10 >
b1110 d
b110 s
1)
#2440000
0)
#2450000
b100 =
b11 >
1)
#2460000
0)
#2470000
b0 =
b100 >
1)
#2480000
0)
#2490000
b1 =
b0 >
1)
#2500000
0)
#2510000
b10 =
b1111 c
b111 r
15
b1 >
1)
#2520000
0)
#2530000
b11 =
b111 s
b1111 d
05
b10 >
1)
#2540000
0)
#2550000
b100 =
b11 >
1)
#2560000
0)
#2570000
b0 =
b100 >
1)
#2580000
0)
#2590000
b1 =
b0 >
1)
#2600000
0)
#2610000
b10 =
b1 a
b0 c
b1000 r
15
b1 >
1)
#2620000
0)
#2630000
b11 =
05
b10 >
b1 b
b0 d
b1000 s
1)
#2640000
0)
#2650000
b100 =
b11 >
1)
#2660000
0)
#2670000
b0 =
b100 >
1)
#2680000
0)
#2690000
b1 =
b0 >
1)
#2700000
0)
#2710000
b10 =
b1 c
b1001 r
15
b1 >
1)
#2720000
0)
#2730000
b11 =
b1001 s
b1 d
05
b10 >
1)
#2740000
0)
#2750000
b100 =
b11 >
1)
#2760000
0)
#2770000
b0 =
b100 >
1)
#2780000
0)
#2790000
b1 =
b0 >
1)
#2800000
0)
#2810000
b10 =
b10 c
b1010 r
15
b1 >
1)
#2820000
0)
#2830000
b11 =
05
b10 >
b10 d
b1010 s
1)
#2840000
0)
#2850000
b100 =
b11 >
1)
#2860000
0)
#2870000
b0 =
b100 >
1)
#2880000
0)
#2890000
b1 =
b0 >
1)
#2900000
0)
#2910000
b10 =
b11 c
b1011 r
15
b1 >
1)
#2920000
0)
#2930000
b11 =
b1011 s
b11 d
05
b10 >
1)
#2940000
0)
#2950000
b100 =
b11 >
1)
#2960000
0)
#2970000
b0 =
b100 >
1)
#2980000
0)
#2990000
b1 =
b0 >
1)
#3000000
0)
#3010000
b10 =
b100 c
b1100 r
15
b1 >
1)
#3020000
0)
#3030000
b11 =
05
b10 >
b100 d
b1100 s
1)
#3040000
0)
#3050000
b100 =
b11 >
1)
#3060000
0)
#3070000
b0 =
b100 >
1)
#3080000
0)
#3090000
b1 =
b0 >
1)
#3100000
0)
#3110000
b10 =
b101 c
b1101 r
15
b1 >
1)
#3120000
0)
#3130000
b11 =
b1101 s
b101 d
05
b10 >
1)
#3140000
0)
#3150000
b100 =
b11 >
1)
#3160000
0)
#3170000
b0 =
b100 >
1)
#3180000
0)
#3190000
b1 =
b0 >
1)
#3200000
0)
#3210000
b10 =
b110 c
b1110 r
15
b1 >
1)
#3220000
0)
#3230000
b11 =
05
b10 >
b110 d
b1110 s
1)
#3240000
0)
#3250000
b100 =
b11 >
1)
#3260000
0)
#3270000
b0 =
b100 >
1)
#3280000
0)
#3290000
b1 =
b0 >
1)
#3300000
0)
#3310000
b10 =
b111 c
b1111 r
15
b1 >
1)
#3320000
0)
#3330000
b11 =
b1111 s
b111 d
05
b10 >
1)
#3340000
0)
#3350000
b100 =
b11 >
1)
#3360000
0)
#3370000
b0 =
b100 >
1)
#3380000
0)
#3390000
b1 =
b0 >
1)
#3400000
0)
#3410000
b10 =
b1000 c
b1 p
b0 r
15
b1 >
1)
#3420000
0)
#3430000
b11 =
05
b10 >
b1000 d
b1 q
b0 s
1)
#3440000
0)
#3450000
b100 =
b11 >
1)
#3460000
0)
#3470000
b0 =
b100 >
1)
#3480000
0)
#3490000
b1 =
b0 >
1)
#3500000
0)
#3510000
b10 =
b1001 c
b1 r
15
b1 >
1)
#3520000
0)
#3530000
b11 =
b1 s
b1001 d
05
b10 >
1)
#3540000
0)
#3550000
b100 =
b11 >
1)
#3560000
0)
#3570000
b0 =
b100 >
1)
#3580000
0)
#3590000
b1 =
b0 >
1)
#3600000
0)
#3610000
b10 =
b1010 c
b10 r
15
b1 >
1)
#3620000
0)
#3630000
b11 =
05
b10 >
b1010 d
b10 s
1)
#3640000
0)
#3650000
b100 =
b11 >
1)
#3660000
0)
#3670000
b0 =
b100 >
1)
#3680000
0)
#3690000
b1 =
b0 >
1)
#3700000
0)
#3710000
b10 =
b1011 c
b11 r
15
b1 >
1)
#3720000
0)
#3730000
b11 =
b11 s
b1011 d
05
b10 >
1)
#3740000
0)
#3750000
b100 =
b11 >
1)
#3760000
0)
#3770000
b0 =
b100 >
1)
#3780000
0)
#3790000
b1 =
b0 >
1)
#3800000
0)
#3810000
b10 =
b1100 c
b100 r
15
b1 >
1)
#3820000
0)
#3830000
b11 =
05
b10 >
b1100 d
b100 s
1)
#3840000
0)
#3850000
b100 =
b11 >
1)
#3860000
0)
#3870000
b0 =
b100 >
1)
#3880000
0)
#3890000
b1 =
b0 >
1)
#3900000
0)
#3910000
b10 =
b1101 c
b101 r
15
b1 >
1)
#3920000
0)
#3930000
b11 =
b101 s
b1101 d
05
b10 >
1)
#3940000
0)
#3950000
b100 =
b11 >
1)
#3960000
0)
#3970000
b0 =
b100 >
1)
#3980000
0)
#3990000
b1 =
b0 >
1)
#4000000
0)
#4010000
b10 =
b1110 c
b110 r
15
b1 >
1)
#4020000
0)
#4030000
b11 =
05
b10 >
b1110 d
b110 s
1)
#4040000
0)
#4050000
b100 =
b11 >
1)
#4060000
0)
#4070000
b0 =
b100 >
1)
#4080000
0)
#4090000
b1 =
b0 >
1)
#4100000
0)
#4110000
b10 =
b1111 c
b111 r
15
b1 >
1)
#4120000
0)
#4130000
b11 =
b111 s
b1111 d
05
b10 >
1)
#4140000
0)
#4150000
b100 =
b11 >
1)
#4160000
0)
#4170000
b0 =
b100 >
1)
#4180000
0)
#4190000
b1 =
b0 >
1)
#4200000
0)
#4210000
b10 =
b10 a
b0 c
b1000 r
15
b1 >
1)
#4220000
0)
#4230000
b11 =
05
b10 >
b10 b
b0 d
b1000 s
1)
#4240000
0)
#4250000
b100 =
b11 >
1)
#4260000
0)
#4270000
b0 =
b100 >
1)
#4280000
0)
#4290000
b1 =
b0 >
1)
#4300000
0)
#4310000
b10 =
b1 c
b1001 r
15
b1 >
1)
#4320000
0)
#4330000
b11 =
b1001 s
b1 d
05
b10 >
1)
#4340000
0)
#4350000
b100 =
b11 >
1)
#4360000
0)
#4370000
b0 =
b100 >
1)
#4380000
0)
#4390000
b1 =
b0 >
1)
#4400000
0)
#4410000
b10 =
b10 c
b1010 r
15
b1 >
1)
#4420000
0)
#4430000
b11 =
05
b10 >
b10 d
b1010 s
1)
#4440000
0)
#4450000
b100 =
b11 >
1)
#4460000
0)
#4470000
b0 =
b100 >
1)
#4480000
0)
#4490000
b1 =
b0 >
1)
#4500000
0)
